iec_api/__init__.py
iec_api/commons.py
iec_api/const.py
iec_api/data.py
iec_api/fault_portal_data.py
iec_api/fault_portal_models/fault_portal_base.py
iec_api/fault_portal_models/outages.py
iec_api/fault_portal_models/user_profile.py
iec_api/iec_client.py
iec_api/login.py
iec_api/masa_api_models/building_options.py
iec_api/masa_api_models/cities.py
iec_api/masa_api_models/equipment.py
iec_api/masa_api_models/lookup.py
iec_api/masa_api_models/order_lookup.py
iec_api/masa_api_models/titles.py
iec_api/masa_api_models/user_profile.py
iec_api/masa_api_models/volt_levels.py
iec_api/masa_data.py
iec_api/models/account.py
iec_api/models/contract.py
iec_api/models/contract_check.py
iec_api/models/customer.py
iec_api/models/device.py
iec_api/models/device_identity.py
iec_api/models/device_type.py
iec_api/models/efs.py
iec_api/models/electric_bill.py
iec_api/models/error_response.py
iec_api/models/exceptions.py
iec_api/models/get_pdf.py
iec_api/models/invoice.py
iec_api/models/jwt.py
iec_api/models/meter_reading.py
iec_api/models/models_commons.py
iec_api/models/okta_errors.py
iec_api/models/outages.py
iec_api/models/remote_reading.py
iec_api/models/response_descriptor.py
iec_api/models/send_consumption_to_mail.py
iec_api/static_data.py
iec_api/usage_calculator/__init__.py
iec_api/usage_calculator/calculator.py
iec_api/usage_calculator/consumption.py
iec_api/usage_calculator/electric_device.py
iec_api/usage_calculator/get_calculator_response.py
iec_api/usage_calculator/rates.py
iec_api-0.4.10.dist-info/LICENSE
iec_api-0.4.10.dist-info/METADATA
iec_api-0.4.10.dist-info/WHEEL
iec_api-0.4.10.dist-info/RECORD
