Metadata-Version: 2.1
Name: iec-api
Version: 0.4.10
Summary: A Python wrapper for Israel Electric Company API
Home-page: https://github.com/GuyKh/py-iec-api
License: MIT
Keywords: python,poetry,api,iec,israel,electric
Author: GuyKh
Maintainer: Guy Khmelnitsky
Maintainer-email: guykhmel@gmail.com
Requires-Python: >=3.10,<4.0
Classifier: License :: OSI Approved :: MIT License
Classifier: Programming Language :: Python :: 3
Classifier: Programming Language :: Python :: 3.10
Classifier: Programming Language :: Python :: 3.11
Classifier: Programming Language :: Python :: 3.12
Classifier: Programming Language :: Python :: 3.13
Requires-Dist: aiofiles (>=23.2.1,<25.0.0)
Requires-Dist: aiohttp (>=3.9.1,<4.0.0)
Requires-Dist: mashumaro (>=3.13,<4.0)
Requires-Dist: pkce (>=1.0.3,<2.0.0)
Requires-Dist: pyjwt (>=2.8.0,<3.0.0)
Requires-Dist: pytz (>=2024.1,<2025.0)
Requires-Dist: requests (>=2.31.0,<3.0.0)
Project-URL: Repository, https://github.com/GuyKh/py-iec-api
